Workbook
Name ContractValue: Inputs!$C$2
Name Months: Inputs!$C$3
Name RetRate: Inputs!$C$4
Name RetCap: Inputs!$C$5
Name AdvFirst: Inputs!$C$6
Name AdvFirstMonth: Inputs!$C$7
Name AdvSecond: Inputs!$C$8
Name AdvSecondMonth: Inputs!$C$9
Name RecRate: Inputs!$C$10
Name RecDeadline: Inputs!$C$11
Name LDRate: Inputs!$C$12
Name LDCap: Inputs!$C$13
Name DelayDays: Inputs!$C$14
Name CostShare: Inputs!$C$15
Name PayLagDays: Inputs!$C$16
Name RelMonths: Inputs!$C$17
Name ODRate: Inputs!$C$18

Sheet Read me
A1: Spec §8.4 hand benchmark (CE725 Team 2, module M4 cash flow)
A3: MANUAL CHECK REQUIRED. The course requires this hand benchmark to be checked by a person.
A4: Open the 'Benchmark 8.4' sheet, redo each line by hand or calculator, and sign below.
A5: Checked by: ____________________ Date: ____________ Result (all MATCH / differences): ______________
A7: What this file is
A8: Every number in 'Monthly' and in column D of 'Benchmark 8.4' is a live Excel formula that reads the
A9: yellow cells in 'Inputs'. Nothing is pasted from Python. Change an input and Excel recalculates.
A10: Column C of 'Benchmark 8.4' is the spec table typed by hand. Column E is the Python engine's value,
A11: written when the file was generated (python -m analyser.cashflow.benchmark, from backend/).
A12: Columns F and G say MATCH when Excel and Python agree with the spec to 4 decimals.
A14: Conventions (same as the Python engine, see backend/analyser/cashflow/FORMULAS.md)
A15: Units: Rs crore. Row = end of month. Month 0 = signing. Work of month m is billed at the end of month m.
... A22: Values not given in spec §8.4 are [ASSUMPTION]s and are marked in 'Inputs'.

Sheet Inputs
A1: Name | B1: Input | C1: Value | D1: Unit / note
A2: ContractValue | B2: Contract value V | C2: 100 | D2: Rs crore
A3: Months | B3: Duration T | C3: 24 | D3: months (even progress, 1/T each month)
A4: RetRate | B4: Retention rate r | C4: 0.06 | D4: share of each gross bill
A5: RetCap | B5: Retention cap Rmax | C5: 0.05 | D5: share of V
A6: AdvFirst | B6: Advance instalment 1 | C6: 0.05 | D6: share of V
A7: AdvFirstMonth | B7: Instalment 1 arrives in month | C7: 0 | D7: month [ASSUMPTION]
A8: AdvSecond | B8: Advance instalment 2 | C8: 0.05 | D8: share of V
A9: AdvSecondMonth | B9: Instalment 2 arrives in month | C9: 2 | D9: month [ASSUMPTION]
A10: RecRate | B10: Advance recovery rate rho | C10: 0.15 | D10: share of each gross bill
A11: RecDeadline | B11: Recovery deadline | C11: 0.8 | D11: share of T
A12: LDRate | B12: Delay damages rate l | C12: 0.0005 | D12: share of V per day
A13: LDCap | B13: Delay damages cap Lmax | C13: 0.1 | D13: share of V
... A18: ODRate | B18: Overdraft rate | C18: 0.1 | D18: per year [ASSUMPTION]

Sheet Benchmark 8.4
A1: Item | B1: Hand calculation | C1: Spec §8.4 result (typed) | D1: Excel formula result | E1: Python engine | F1: Excel = spec? | G1: Python = spec?
A2: Gross work each month (Rs crore) | B2: 100 / 24 | C2: 4.1667 | D2: =Monthly!B3 | E2: 4.1666667 | F2: =IF(ABS(ROUND(D2,4)-C2)<0.00005,"MATCH","CHECK") | G2: =IF(ABS(ROUND(E2,4)-C2)<0.00005,"MATCH","CHECK")
A3: Retention each month (Rs crore) | B3: 6% of 4.1667 | C3: 0.25 | D3: =Monthly!C3 | E3: 0.25 | F3: =IF(ABS(ROUND(D3,4)-C3)<0.00005,"MATCH","CHECK") | G3: =IF(ABS(ROUND(E3,4)-C3)<0.00005,"MATCH","CHECK")
A4: Month in which retention reaches its 5% cap (Rs 5 crore) | B4: 5 / 0.25 | C4: 20 | D4: =MIN(Monthly!S2:S32) | E4: 20 | F4: =IF(ABS(ROUND(D4,4)-C4)<0.00005,"MATCH","CHECK") | G4: =IF(ABS(ROUND(E4,4)-C4)<0.00005,"MATCH","CHECK")
A5: Advance recovery each month (Rs crore) | B5: 15% of 4.1667 | C5: 0.625 | D5: =Monthly!G3 | E5: 0.625 | F5: =IF(ABS(ROUND(D5,4)-C5)<0.00005,"MATCH","CHECK") | G5: =IF(ABS(ROUND(E5,4)-C5)<0.00005,"MATCH","CHECK")
A6: Month in which a Rs 10 crore advance is fully recovered | B6: 10 / 0.625 | C6: 16 | D6: =MIN(Monthly!T2:T32) | E6: 16 | F6: =IF(ABS(ROUND(D6,4)-C6)<0.00005,"MATCH","CHECK") | G6: =IF(ABS(ROUND(E6,4)-C6)<0.00005,"MATCH","CHECK")
A7: 80% recovery limit (month) | B7: 0.8 x 24 | C7: 19.2 | D7: =RecDeadline*Months | E7: 19.2 | F7: =IF(ABS(ROUND(D7,4)-C7)<0.00005,"MATCH","CHECK") | G7: =IF(ABS(ROUND(E7,4)-C7)<0.00005,"MATCH","CHECK")
A8: Net certified in month 1 (Rs crore) | B8: 4.1667 - 0.25 - 0.625 | C8: 3.2917 | D8: =Monthly!J3 | E8: 3.2916667 | F8: =IF(ABS(ROUND(D8,4)-C8)<0.00005,"MATCH","CHECK") | G8: =IF(ABS(ROUND(E8,4)-C8)<0.00005,"MATCH","CHECK")
A9: Delay damages for 60 days (Rs crore) | B9: 60 x 0.05% of 100 | C9: 3 | D9: =MIN(LDRate*DelayDays,LDCap)*ContractValue | E9: 3 | F9: =IF(ABS(ROUND(D9,4)-C9)<0.00005,"MATCH","CHECK") | G9: =IF(ABS(ROUND(E9,4)-C9)<0.00005,"MATCH","CHECK")
A10: Days of delay to reach the cap | B10: 10% / 0.05% | C10: 200 | D10: =LDCap/LDRate | E10: 200 | F10: =IF(ABS(ROUND(D10,4)-C10)<0.00005,"MATCH","CHECK") | G10: =IF(ABS(ROUND(E10,4)-C10)<0.00005,"MATCH","CHECK")
A11: Delay damages at the cap (Rs crore) | B11: 10% of 100 | C11: 10 | D11: =LDCap*ContractValue | E11: 10 | F11: =IF(ABS(ROUND(D11,4)-C11)<0.00005,"MATCH","CHECK") | G11: =IF(ABS(ROUND(E11,4)-C11)<0.00005,"MATCH","CHECK")
A14: Beyond the spec table (Excel vs Python only; no spec value)
A15: Item | D15: Excel formula result | E15: Python engine | F15: Excel = Python?
A16: Peak funding need = largest positive gap, 0 if none (Rs crore) | D16: =MAX(0,MAX(Monthly!Q2:Q32)) | E16: 0 | F16: =IF(ABS(D16-E16)<0.00005,"MATCH","CHECK")
A17: Month of peak funding (0 if never short of cash) | D17: =IF(MAX(Monthly!Q2:Q32)<=0,0,INDEX(Monthly!A2:A32,MATCH(MAX(Monthly!Q2:Q32),Monthly!Q2:Q32,0))) | E17: 0 | F17: =IF(ABS(D17-E17)<0.00005,"MATCH","CHECK")
A18: Overdraft interest = sum of positive gaps x rate / 12 (Rs crore) | D18: =SUMIF(Monthly!Q2:Q32,">0")*ODRate/12 | E18: 0 | F18: =IF(ABS(D18-E18)<0.00005,"MATCH","CHECK")
A19: Total cash in = V - delay damages (Rs crore) | D19: =Monthly!O32 | E19: 97 | F19: =IF(ABS(D19-E19)<0.00005,"MATCH","CHECK")
A20: Total cash out = c x V (Rs crore) | D20: =Monthly!P32 | E20: 85 | F20: =IF(ABS(D20-E20)<0.00005,"MATCH","CHECK")
A21: Largest monthly difference, Excel gap vs Python gap (Rs crore) | D21: =MAX(ABS(MAX('Python monthly'!E2:E32)),ABS(MIN('Python monthly'!E2:E32))) | E21: 0 | F21: =IF(D21<0.00005,"MATCH","CHECK")

Sheet Monthly
A1: Month | B1: Gross work B | C1: Retention Ret | D1: Cum retention | E1: Advance received | F1: Cum advance received | G1: Advance recovery Rec | H1: Cum recovered | I1: Advance outstanding | J1: Net certified | K1: Retention released | L1: Delay damages deducted | M1: Cash in | N1: Cash out | O1: Cum in | P1: Cum out | Q1: Gap (out - in) | R1: Retention held | S1: Cap reached? (month or 999) | T1: Advance repaid? (month or 999)
A2: 0 | B2: =IF(AND(A2>=1,A2<=Months),ContractValue/Months,0) | C2: =MAX(0,MIN(RetRate*B2,RetCap*ContractValue-0)) | D2: =0+C2 | E2: =IF(A2=AdvFirstMonth,AdvFirst*ContractValue,0)+IF(A2=AdvSecondMonth,AdvSecond*ContractValue,0) | F2: =0+E2 | G2: =IF(A2=0,0,IF(OR(A2>=Months,A2>=MAX(1,FLOOR(RecDeadline*Months,1))),F2-0,MIN(RecRate*B2,F2-0))) | H2: =0+G2 | I2: =F2-H2 | J2: =B2-C2-G2 | K2: =IF(A2=Months+DelayDays/30+RelMonths,MAX($D$2:$D$40),0) | L2: =IF(A2=Months+DelayDays/30,'Benchmark 8.4'!$D$9,0) | M2: =IF(A2-PayLagDays/30>=0,OFFSET(J2,-PayLagDays/30,0),0)+E2+K2-L2 | N2: =CostShare*B2 | O2: =0+M2 | P2: =0+N2 | Q2: =P2-O2 | R2: =D2-SUM($K$2:K2) | S2: =IF(D2>=RetCap*ContractValue-0.000001,A2,999) | T2: =IF(AND(A2>=1,H2>=(AdvFirst+AdvSecond)*ContractValue-0.000001),A2,999)
A3: 1 | B3: =IF(AND(A3>=1,A3<=Months),ContractValue/Months,0) | C3: =MAX(0,MIN(RetRate*B3,RetCap*ContractValue-D2)) | D3: =D2+C3 | E3: =IF(A3=AdvFirstMonth,AdvFirst*ContractValue,0)+IF(A3=AdvSecondMonth,AdvSecond*ContractValue,0) | F3: =F2+E3 | G3: =IF(A3=0,0,IF(OR(A3>=Months,A3>=MAX(1,FLOOR(RecDeadline*Months,1))),F3-H2,MIN(RecRate*B3,F3-H2))) | H3: =H2+G3 | I3: =F3-H3 | J3: =B3-C3-G3 | K3: =IF(A3=Months+DelayDays/30+RelMonths,MAX($D$2:$D$40),0) | L3: =IF(A3=Months+DelayDays/30,'Benchmark 8.4'!$D$9,0) | M3: =IF(A3-PayLagDays/30>=0,OFFSET(J3,-PayLagDays/30,0),0)+E3+K3-L3 | N3: =CostShare*B3 | O3: =O2+M3 | P3: =P2+N3 | Q3: =P3-O3 | R3: =D3-SUM($K$2:K3) | S3: =IF(D3>=RetCap*ContractValue-0.000001,A3,999) | T3: =IF(AND(A3>=1,H3>=(AdvFirst+AdvSecond)*ContractValue-0.000001),A3,999)
A4: 2 | B4: =IF(AND(A4>=1,A4<=Months),ContractValue/Months,0) | C4: =MAX(0,MIN(RetRate*B4,RetCap*ContractValue-D3)) | D4: =D3+C4 | E4: =IF(A4=AdvFirstMonth,AdvFirst*ContractValue,0)+IF(A4=AdvSecondMonth,AdvSecond*ContractValue,0) | F4: =F3+E4 | G4: =IF(A4=0,0,IF(OR(A4>=Months,A4>=MAX(1,FLOOR(RecDeadline*Months,1))),F4-H3,MIN(RecRate*B4,F4-H3))) | H4: =H3+G4 | I4: =F4-H4 | J4: =B4-C4-G4 | K4: =IF(A4=Months+DelayDays/30+RelMonths,MAX($D$2:$D$40),0) | L4: =IF(A4=Months+DelayDays/30,'Benchmark 8.4'!$D$9,0) | M4: =IF(A4-PayLagDays/30>=0,OFFSET(J4,-PayLagDays/30,0),0)+E4+K4-L4 | N4: =CostShare*B4 | O4: =O3+M4 | P4: =P3+N4 | Q4: =P4-O4 | R4: =D4-SUM($K$2:K4) | S4: =IF(D4>=RetCap*ContractValue-0.000001,A4,999) | T4: =IF(AND(A4>=1,H4>=(AdvFirst+AdvSecond)*ContractValue-0.000001),A4,999)
A5: 3 | B5: =IF(AND(A5>=1,A5<=Months),ContractValue/Months,0) | C5: =MAX(0,MIN(RetRate*B5,RetCap*ContractValue-D4)) | D5: =D4+C5 | E5: =IF(A5=AdvFirstMonth,AdvFirst*ContractValue,0)+IF(A5=AdvSecondMonth,AdvSecond*ContractValue,0) | F5: =F4+E5 | G5: =IF(A5=0,0,IF(OR(A5>=Months,A5>=MAX(1,FLOOR(RecDeadline*Months,1))),F5-H4,MIN(RecRate*B5,F5-H4))) | H5: =H4+G5 | I5: =F5-H5 | J5: =B5-C5-G5 | K5: =IF(A5=Months+DelayDays/30+RelMonths,MAX($D$2:$D$40),0) | L5: =IF(A5=Months+DelayDays/30,'Benchmark 8.4'!$D$9,0) | M5: =IF(A5-PayLagDays/30>=0,OFFSET(J5,-PayLagDays/30,0),0)+E5+K5-L5 | N5: =CostShare*B5 | O5: =O4+M5 | P5: =P4+N5 | Q5: =P5-O5 | R5: =D5-SUM($K$2:K5) | S5: =IF(D5>=RetCap*ContractValue-0.000001,A5,999) | T5: =IF(AND(A5>=1,H5>=(AdvFirst+AdvSecond)*ContractValue-0.000001),A5,999)
A6: 4 | B6: =IF(AND(A6>=1,A6<=Months),ContractValue/Months,0) | C6: =MAX(0,MIN(RetRate*B6,RetCap*ContractValue-D5)) | D6: =D5+C6 | E6: =IF(A6=AdvFirstMonth,AdvFirst*ContractValue,0)+IF(A6=AdvSecondMonth,AdvSecond*ContractValue,0) | F6: =F5+E6 | G6: =IF(A6=0,0,IF(OR(A6>=Months,A6>=MAX(1,FLOOR(RecDeadline*Months,1))),F6-H5,MIN(RecRate*B6,F6-H5))) | H6: =H5+G6 | I6: =F6-H6 | J6: =B6-C6-G6 | K6: =IF(A6=Months+DelayDays/30+RelMonths,MAX($D$2:$D$40),0) | L6: =IF(A6=Months+DelayDays/30,'Benchmark 8.4'!$D$9,0) | M6: =IF(A6-PayLagDays/30>=0,OFFSET(J6,-PayLagDays/30,0),0)+E6+K6-L6 | N6: =CostShare*B6 | O6: =O5+M6 | P6: =P5+N6 | Q6: =P6-O6 | R6: =D6-SUM($K$2:K6) | S6: =IF(D6>=RetCap*ContractValue-0.000001,A6,999) | T6: =IF(AND(A6>=1,H6>=(AdvFirst+AdvSecond)*ContractValue-0.000001),A6,999)
A7: 5 | B7: =IF(AND(A7>=1,A7<=Months),ContractValue/Months,0) | C7: =MAX(0,MIN(RetRate*B7,RetCap*ContractValue-D6)) | D7: =D6+C7 | E7: =IF(A7=AdvFirstMonth,AdvFirst*ContractValue,0)+IF(A7=AdvSecondMonth,AdvSecond*ContractValue,0) | F7: =F6+E7 | G7: =IF(A7=0,0,IF(OR(A7>=Months,A7>=MAX(1,FLOOR(RecDeadline*Months,1))),F7-H6,MIN(RecRate*B7,F7-H6))) | H7: =H6+G7 | I7: =F7-H7 | J7: =B7-C7-G7 | K7: =IF(A7=Months+DelayDays/30+RelMonths,MAX($D$2:$D$40),0) | L7: =IF(A7=Months+DelayDays/30,'Benchmark 8.4'!$D$9,0) | M7: =IF(A7-PayLagDays/30>=0,OFFSET(J7,-PayLagDays/30,0),0)+E7+K7-L7 | N7: =CostShare*B7 | O7: =O6+M7 | P7: =P6+N7 | Q7: =P7-O7 | R7: =D7-SUM($K$2:K7) | S7: =IF(D7>=RetCap*ContractValue-0.000001,A7,999) | T7: =IF(AND(A7>=1,H7>=(AdvFirst+AdvSecond)*ContractValue-0.000001),A7,999)
A8: 6 | B8: =IF(AND(A8>=1,A8<=Months),ContractValue/Months,0) | C8: =MAX(0,MIN(RetRate*B8,RetCap*ContractValue-D7)) | D8: =D7+C8 | E8: =IF(A8=AdvFirstMonth,AdvFirst*ContractValue,0)+IF(A8=AdvSecondMonth,AdvSecond*ContractValue,0) | F8: =F7+E8 | G8: =IF(A8=0,0,IF(OR(A8>=Months,A8>=MAX(1,FLOOR(RecDeadline*Months,1))),F8-H7,MIN(RecRate*B8,F8-H7))) | H8: =H7+G8 | I8: =F8-H8 | J8: =B8-C8-G8 | K8: =IF(A8=Months+DelayDays/30+RelMonths,MAX($D$2:$D$40),0) | L8: =IF(A8=Months+DelayDays/30,'Benchmark 8.4'!$D$9,0) | M8: =IF(A8-PayLagDays/30>=0,OFFSET(J8,-PayLagDays/30,0),0)+E8+K8-L8 | N8: =CostShare*B8 | O8: =O7+M8 | P8: =P7+N8 | Q8: =P8-O8 | R8: =D8-SUM($K$2:K8) | S8: =IF(D8>=RetCap*ContractValue-0.000001,A8,999) | T8: =IF(AND(A8>=1,H8>=(AdvFirst+AdvSecond)*ContractValue-0.000001),A8,999)
A9: 7 | B9: =IF(AND(A9>=1,A9<=Months),ContractValue/Months,0) | C9: =MAX(0,MIN(RetRate*B9,RetCap*ContractValue-D8)) | D9: =D8+C9 | E9: =IF(A9=AdvFirstMonth,AdvFirst*ContractValue,0)+IF(A9=AdvSecondMonth,AdvSecond*ContractValue,0) | F9: =F8+E9 | G9: =IF(A9=0,0,IF(OR(A9>=Months,A9>=MAX(1,FLOOR(RecDeadline*Months,1))),F9-H8,MIN(RecRate*B9,F9-H8))) | H9: =H8+G9 | I9: =F9-H9 | J9: =B9-C9-G9 | K9: =IF(A9=Months+DelayDays/30+RelMonths,MAX($D$2:$D$40),0) | L9: =IF(A9=Months+DelayDays/30,'Benchmark 8.4'!$D$9,0) | M9: =IF(A9-PayLagDays/30>=0,OFFSET(J9,-PayLagDays/30,0),0)+E9+K9-L9 | N9: =CostShare*B9 | O9: =O8+M9 | P9: =P8+N9 | Q9: =P9-O9 | R9: =D9-SUM($K$2:K9) | S9: =IF(D9>=RetCap*ContractValue-0.000001,A9,999) | T9: =IF(AND(A9>=1,H9>=(AdvFirst+AdvSecond)*ContractValue-0.000001),A9,999)
A10: 8 | B10: =IF(AND(A10>=1,A10<=Months),ContractValue/Months,0) | C10: =MAX(0,MIN(RetRate*B10,RetCap*ContractValue-D9)) | D10: =D9+C10 | E10: =IF(A10=AdvFirstMonth,AdvFirst*ContractValue,0)+IF(A10=AdvSecondMonth,AdvSecond*ContractValue,0) | F10: =F9+E10 | G10: =IF(A10=0,0,IF(OR(A10>=Months,A10>=MAX(1,FLOOR(RecDeadline*Months,1))),F10-H9,MIN(RecRate*B10,F10-H9))) | H10: =H9+G10 | I10: =F10-H10 | J10: =B10-C10-G10 | K10: =IF(A10=Months+DelayDays/30+RelMonths,MAX($D$2:$D$40),0) | L10: =IF(A10=Months+DelayDays/30,'Benchmark 8.4'!$D$9,0) | M10: =IF(A10-PayLagDays/30>=0,OFFSET(J10,-PayLagDays/30,0),0)+E10+K10-L10 | N10: =CostShare*B10 | O10: =O9+M10 | P10: =P9+N10 | Q10: =P10-O10 | R10: =D10-SUM($K$2:K10) | S10: =IF(D10>=RetCap*ContractValue-0.000001,A10,999) | T10: =IF(AND(A10>=1,H10>=(AdvFirst+AdvSecond)*ContractValue-0.000001),A10,999)
A11: 9 | B11: =IF(AND(A11>=1,A11<=Months),ContractValue/Months,0) | C11: =MAX(0,MIN(RetRate*B11,RetCap*ContractValue-D10)) | D11: =D10+C11 | E11: =IF(A11=AdvFirstMonth,AdvFirst*ContractValue,0)+IF(A11=AdvSecondMonth,AdvSecond*ContractValue,0) | F11: =F10+E11 | G11: =IF(A11=0,0,IF(OR(A11>=Months,A11>=MAX(1,FLOOR(RecDeadline*Months,1))),F11-H10,MIN(RecRate*B11,F11-H10))) | H11: =H10+G11 | I11: =F11-H11 | J11: =B11-C11-G11 | K11: =IF(A11=Months+DelayDays/30+RelMonths,MAX($D$2:$D$40),0) | L11: =IF(A11=Months+DelayDays/30,'Benchmark 8.4'!$D$9,0) | M11: =IF(A11-PayLagDays/30>=0,OFFSET(J11,-PayLagDays/30,0),0)+E11+K11-L11 | N11: =CostShare*B11 | O11: =O10+M11 | P11: =P10+N11 | Q11: =P11-O11 | R11: =D11-SUM($K$2:K11) | S11: =IF(D11>=RetCap*ContractValue-0.000001,A11,999) | T11: =IF(AND(A11>=1,H11>=(AdvFirst+AdvSecond)*ContractValue-0.000001),A11,999)
A12: 10 | B12: =IF(AND(A12>=1,A12<=Months),ContractValue/Months,0) | C12: =MAX(0,MIN(RetRate*B12,RetCap*ContractValue-D11)) | D12: =D11+C12 | E12: =IF(A12=AdvFirstMonth,AdvFirst*ContractValue,0)+IF(A12=AdvSecondMonth,AdvSecond*ContractValue,0) | F12: =F11+E12 | G12: =IF(A12=0,0,IF(OR(A12>=Months,A12>=MAX(1,FLOOR(RecDeadline*Months,1))),F12-H11,MIN(RecRate*B12,F12-H11))) | H12: =H11+G12 | I12: =F12-H12 | J12: =B12-C12-G12 | K12: =IF(A12=Months+DelayDays/30+RelMonths,MAX($D$2:$D$40),0) | L12: =IF(A12=Months+DelayDays/30,'Benchmark 8.4'!$D$9,0) | M12: =IF(A12-PayLagDays/30>=0,OFFSET(J12,-PayLagDays/30,0),0)+E12+K12-L12 | N12: =CostShare*B12 | O12: =O11+M12 | P12: =P11+N12 | Q12: =P12-O12 | R12: =D12-SUM($K$2:K12) | S12: =IF(D12>=RetCap*ContractValue-0.000001,A12,999) | T12: =IF(AND(A12>=1,H12>=(AdvFirst+AdvSecond)*ContractValue-0.000001),A12,999)
A13: 11 | B13: =IF(AND(A13>=1,A13<=Months),ContractValue/Months,0) | C13: =MAX(0,MIN(RetRate*B13,RetCap*ContractValue-D12)) | D13: =D12+C13 | E13: =IF(A13=AdvFirstMonth,AdvFirst*ContractValue,0)+IF(A13=AdvSecondMonth,AdvSecond*ContractValue,0) | F13: =F12+E13 | G13: =IF(A13=0,0,IF(OR(A13>=Months,A13>=MAX(1,FLOOR(RecDeadline*Months,1))),F13-H12,MIN(RecRate*B13,F13-H12))) | H13: =H12+G13 | I13: =F13-H13 | J13: =B13-C13-G13 | K13: =IF(A13=Months+DelayDays/30+RelMonths,MAX($D$2:$D$40),0) | L13: =IF(A13=Months+DelayDays/30,'Benchmark 8.4'!$D$9,0) | M13: =IF(A13-PayLagDays/30>=0,OFFSET(J13,-PayLagDays/30,0),0)+E13+K13-L13 | N13: =CostShare*B13 | O13: =O12+M13 | P13: =P12+N13 | Q13: =P13-O13 | R13: =D13-SUM($K$2:K13) | S13: =IF(D13>=RetCap*ContractValue-0.000001,A13,999) | T13: =IF(AND(A13>=1,H13>=(AdvFirst+AdvSecond)*ContractValue-0.000001),A13,999)
A14: 12 | B14: =IF(AND(A14>=1,A14<=Months),ContractValue/Months,0) | C14: =MAX(0,MIN(RetRate*B14,RetCap*ContractValue-D13)) | D14: =D13+C14 | E14: =IF(A14=AdvFirstMonth,AdvFirst*ContractValue,0)+IF(A14=AdvSecondMonth,AdvSecond*ContractValue,0) | F14: =F13+E14 | G14: =IF(A14=0,0,IF(OR(A14>=Months,A14>=MAX(1,FLOOR(RecDeadline*Months,1))),F14-H13,MIN(RecRate*B14,F14-H13))) | H14: =H13+G14 | I14: =F14-H14 | J14: =B14-C14-G14 | K14: =IF(A14=Months+DelayDays/30+RelMonths,MAX($D$2:$D$40),0) | L14: =IF(A14=Months+DelayDays/30,'Benchmark 8.4'!$D$9,0) | M14: =IF(A14-PayLagDays/30>=0,OFFSET(J14,-PayLagDays/30,0),0)+E14+K14-L14 | N14: =CostShare*B14 | O14: =O13+M14 | P14: =P13+N14 | Q14: =P14-O14 | R14: =D14-SUM($K$2:K14) | S14: =IF(D14>=RetCap*ContractValue-0.000001,A14,999) | T14: =IF(AND(A14>=1,H14>=(AdvFirst+AdvSecond)*ContractValue-0.000001),A14,999)
... A32: 30 | B32: =IF(AND(A32>=1,A32<=Months),ContractValue/Months,0) | C32: =MAX(0,MIN(RetRate*B32,RetCap*ContractValue-D31)) | D32: =D31+C32 | E32: =IF(A32=AdvFirstMonth,AdvFirst*ContractValue,0)+IF(A32=AdvSecondMonth,AdvSecond*ContractValue,0) | F32: =F31+E32 | G32: =IF(A32=0,0,IF(OR(A32>=Months,A32>=MAX(1,FLOOR(RecDeadline*Months,1))),F32-H31,MIN(RecRate*B32,F32-H31))) | H32: =H31+G32 | I32: =F32-H32 | J32: =B32-C32-G32 | K32: =IF(A32=Months+DelayDays/30+RelMonths,MAX($D$2:$D$40),0) | L32: =IF(A32=Months+DelayDays/30,'Benchmark 8.4'!$D$9,0) | M32: =IF(A32-PayLagDays/30>=0,OFFSET(J32,-PayLagDays/30,0),0)+E32+K32-L32 | N32: =CostShare*B32 | O32: =O31+M32 | P32: =P31+N32 | Q32: =P32-O32 | R32: =D32-SUM($K$2:K32) | S32: =IF(D32>=RetCap*ContractValue-0.000001,A32,999) | T32: =IF(AND(A32>=1,H32>=(AdvFirst+AdvSecond)*ContractValue-0.000001),A32,999)

Sheet Python monthly
A1: Month | B1: Python cash in | C1: Python cash out | D1: Python gap | E1: Excel gap - Python gap
A2: 0 | B2: 5 | C2: 0 | D2: -5 | E2: =Monthly!Q2-D2
A3: 1 | B3: 0 | C3: 3.5416667 | D3: -1.4583333 | E3: =Monthly!Q3-D3
A4: 2 | B4: 8.2916667 | C4: 3.5416667 | D4: -6.2083333 | E4: =Monthly!Q4-D4
A5: 3 | B5: 3.2916667 | C5: 3.5416667 | D5: -5.9583333 | E5: =Monthly!Q5-D5
A6: 4 | B6: 3.2916667 | C6: 3.5416667 | D6: -5.7083333 | E6: =Monthly!Q6-D6
A7: 5 | B7: 3.2916667 | C7: 3.5416667 | D7: -5.4583333 | E7: =Monthly!Q7-D7
A8: 6 | B8: 3.2916667 | C8: 3.5416667 | D8: -5.2083333 | E8: =Monthly!Q8-D8
A9: 7 | B9: 3.2916667 | C9: 3.5416667 | D9: -4.9583333 | E9: =Monthly!Q9-D9
A10: 8 | B10: 3.2916667 | C10: 3.5416667 | D10: -4.7083333 | E10: =Monthly!Q10-D10
A11: 9 | B11: 3.2916667 | C11: 3.5416667 | D11: -4.4583333 | E11: =Monthly!Q11-D11
A12: 10 | B12: 3.2916667 | C12: 3.5416667 | D12: -4.2083333 | E12: =Monthly!Q12-D12
A13: 11 | B13: 3.2916667 | C13: 3.5416667 | D13: -3.9583333 | E13: =Monthly!Q13-D13
... A29: 27 | B29: 5 | C29: 0 | D29: -12 | E29: =Monthly!Q29-D29
